{"trial_id": "0155", "hyperparameters": {"space": [{"class_name": "Int", "config": {"name": "units", "default": null, "conditions": [], "min_value": 10, "max_value": 50, "step": 5, "sampling": "linear"}}, {"class_name": "Float", "config": {"name": "dropout_value", "default": 0.0, "conditions": [], "min_value": 0.0, "max_value": 0.5, "step": 0.1, "sampling": "linear"}}, {"class_name": "Choice", "config": {"name": "optimizer", "default": "rmsprop", "conditions": [], "values": ["rmsprop", "nadam", "adam"], "ordered": false}}], "values": {"units": 30, "dropout_value": 0.0, "optimizer": "rmsprop", "tuner/epochs": 4, "tuner/initial_epoch": 0, "tuner/bracket": 3, "tuner/round": 0}}, "metrics": {"metrics": {"accuracy": {"direction": "max", "observations": [{"value": [0.8543025851249695], "step": 2}]}, "loss": {"direction": "min", "observations": [{"value": [0.31442204117774963], "step": 2}]}, "precision": {"direction": "max", "observations": [{"value": [0.7351388335227966], "step": 2}]}, "recall": {"direction": "max", "observations": [{"value": [0.6142897605895996], "step": 2}]}, "val_accuracy": {"direction": "max", "observations": [{"value": [0.8603634238243103], "step": 2}]}, "val_loss": {"direction": "min", "observations": [{"value": [0.30338254570961], "step": 2}]}, "val_precision": {"direction": "max", "observations": [{"value": [0.7748240828514099], "step": 2}]}, "val_recall": {"direction": "max", "observations": [{"value": [0.5744927525520325], "step": 2}]}}}, "score": 0.8603634238243103, "best_step": 2, "status": "COMPLETED", "message": null}